agent_reasoning/__init__.py
agent_reasoning/cli.py
agent_reasoning/client.py
agent_reasoning/config.py
agent_reasoning/ensemble.py
agent_reasoning/interceptor.py
agent_reasoning/server.py
agent_reasoning/agents/__init__.py
agent_reasoning/agents/base.py
agent_reasoning/agents/consistency.py
agent_reasoning/agents/cot.py
agent_reasoning/agents/decomposed.py
agent_reasoning/agents/least_to_most.py
agent_reasoning/agents/react.py
agent_reasoning/agents/recursive.py
agent_reasoning/agents/self_reflection.py
agent_reasoning/agents/standard.py
agent_reasoning/agents/tot.py
agent_reasoning/visualization/__init__.py
agent_reasoning/visualization/base.py
agent_reasoning/visualization/diff_viz.py
agent_reasoning/visualization/models.py
agent_reasoning/visualization/step_viz.py
agent_reasoning/visualization/swimlane_viz.py
agent_reasoning/visualization/task_viz.py
agent_reasoning/visualization/tree_viz.py
agent_reasoning/visualization/voting_viz.py
agent_reasoning-1.0.7.dist-info/licenses/LICENSE
agents/base.py
agents/consistency.py
agents/cot.py
agents/decomposed.py
agents/least_to_most.py
agents/react.py
agents/recursive.py
agents/self_reflection.py
agents/standard.py
agents/tot.py
visualization/__init__.py
visualization/base.py
visualization/diff_viz.py
visualization/models.py
visualization/step_viz.py
visualization/swimlane_viz.py
visualization/task_viz.py
visualization/tree_viz.py
visualization/voting_viz.py
agent_reasoning-1.0.7.dist-info/METADATA
agent_reasoning-1.0.7.dist-info/WHEEL
agent_reasoning-1.0.7.dist-info/entry_points.txt
agent_reasoning-1.0.7.dist-info/top_level.txt
agent_reasoning-1.0.7.dist-info/RECORD
